TeraTTS/__init__.py
TeraTTS/infer_onnx.py
TeraTTS/tokenizer/__init__.py
TeraTTS/tokenizer/g2p/__init__.py
TeraTTS/tokenizer/g2p/g2p.py
TeraTTS/tokenizer/g2p/tokenizer.py
TeraTTS-1.0.dist-info/LICENSE.txt
TeraTTS-1.0.dist-info/METADATA
TeraTTS-1.0.dist-info/WHEEL
TeraTTS-1.0.dist-info/top_level.txt
TeraTTS-1.0.dist-info/RECORD
